MANIFEST.in
README.txt
requirements.txt
setup.cfg
setup.py
test_requirements.txt
version.txt
cloudshell/__init__.py
cloudshell/networking/__init__.py
cloudshell/networking/cisco/__init__.py
cloudshell/networking/cisco/iosxr/__init__.py
cloudshell/networking/cisco/iosxr/cisco_iosxr_autoload_operations.py
cloudshell/networking/cisco/iosxr/cisco_iosxr_bootstrap.py
cloudshell/networking/cisco/iosxr/cisco_iosxr_configuration.py
cloudshell/networking/cisco/iosxr/cisco_iosxr_configuration_operations.py
cloudshell/networking/cisco/iosxr/cisco_iosxr_handler.py
cloudshell/networking/cisco/iosxr/cisco_iosxr_resource_driver.py
cloudshell/networking/cisco/iosxr/test_iosxr.py
cloudshell_networking_cisco_iosxr_beta.egg-info/PKG-INFO
cloudshell_networking_cisco_iosxr_beta.egg-info/SOURCES.txt
cloudshell_networking_cisco_iosxr_beta.egg-info/dependency_links.txt
cloudshell_networking_cisco_iosxr_beta.egg-info/requires.txt
cloudshell_networking_cisco_iosxr_beta.egg-info/top_level.txt