Metadata-Version: 1.0
Name: cloudshell-networking-cisco-iosxr-beta
Version: 1.0.19
Summary: QualiSystems networking cisco IOS-XR specific Package
Home-page: http://www.qualisystems.com/
Author: QualiSystems
Author-email: info@qualisystems.com
License: UNKNOWN
Platform: UNKNOWN
